setup.py
keybin_client/__init__.py
keybin_client/errors.py
keybin_client/keybin.py
keybin_client.egg-info/PKG-INFO
keybin_client.egg-info/SOURCES.txt
keybin_client.egg-info/dependency_links.txt
keybin_client.egg-info/not-zip-safe
keybin_client.egg-info/requires.txt
keybin_client.egg-info/top_level.txt