Metadata-Version: 1.0
Name: keybin-client
Version: 0.1
Summary: Keybin client library
Home-page: https://github.com/MarcDufresne/keybin-client
Author: MarcDufresne
Author-email: marc.andre.dufresne@gmail.com
License: UNKNOWN
Platform: UNKNOWN
